mini_cryptography/__init__.py
mini_cryptography/ecdsa.py
mini_cryptography/merkle.py
mini_cryptography/tests/__init__.py
mini_cryptography/tests/ECDSA/__init__.py
mini_cryptography/tests/ECDSA/test_ecdsa.py
mini_cryptography/tests/ECDSA/test_ecdsa_point.py
mini_cryptography/tests/Merkle/__init__.py
mini_cryptography/tests/Merkle/test_merkle.py
mini_cryptography-0.0.2.dist-info/LICENSE
mini_cryptography-0.0.2.dist-info/METADATA
mini_cryptography-0.0.2.dist-info/WHEEL
mini_cryptography-0.0.2.dist-info/top_level.txt
mini_cryptography-0.0.2.dist-info/RECORD
