Metadata-Version: 2.1
Name: mini-cryptography
Version: 0.0.2
Summary: Package that contains ECDSA arithmetics and Merkle tree root calculation
Home-page: https://github.com/antanasbendoraitis/mini-cryptography.git
Author: Antanas Bendoraitis
Author-email: antanasbendoraitis7@gmail.com
Project-URL: Bug Tracker, https://github.com/Duomenu-saugojimo-sistema/Duomenu-saugojimo-sistema-paremta-bloku-grandines-technologija/issues
Classifier: Programming Language :: Python :: 3
Classifier: License :: OSI Approved :: GNU General Public License v3 or later (GPLv3+)
Classifier: Operating System :: OS Independent
Requires-Python: >=3.7
License-File: LICENSE
Requires-Dist: tinyec
